[{"attrs":{},"parents":[],"uid":{"__entity":{"id":"Teacher","type":"Role"}}},{"attrs":{},"parents":[],"uid":{"__entity":{"id":"TA","type":"Role"}}},{"attrs":{},"parents":[{"__entity":{"id":"T0C1","type":"Course"}},{"__entity":{"id":"T0C0","type":"Course"}},{"__entity":{"id":"T1C0","type":"Course"}}],"uid":{"__entity":{"id":"Stu0","type":"Student"}}},{"attrs":{},"parents":[{"__entity":{"id":"T0C0","type":"Course"}}],"uid":{"__entity":{"id":"Stu1","type":"Student"}}},{"attrs":{},"parents":[{"__entity":{"id":"T0C1","type":"Course"}}],"uid":{"__entity":{"id":"Stu2","type":"Student"}}},{"attrs":{},"parents":[{"__entity":{"id":"T0C0","type":"Course"}},{"__entity":{"id":"T0C1","type":"Course"}},{"__entity":{"id":"T1C0","type":"Course"}}],"uid":{"__entity":{"id":"Stu3","type":"Student"}}},{"attrs":{},"parents":[{"__entity":{"id":"T0C0","type":"Course"}},{"__entity":{"id":"T1C0","type":"Course"}},{"__entity":{"id":"T0C1","type":"Course"}}],"uid":{"__entity":{"id":"Stu4","type":"Student"}}},{"attrs":{},"parents":[{"__entity":{"id":"T1C0","type":"Course"}},{"__entity":{"id":"T0C0","type":"Course"}},{"__entity":{"id":"T0C1","type":"Course"}}],"uid":{"__entity":{"id":"Stu5","type":"Student"}}},{"attrs":{},"parents":[{"__entity":{"id":"T0C1","type":"Course"}},{"__entity":{"id":"T0C0","type":"Course"}}],"uid":{"__entity":{"id":"Stu6","type":"Student"}}},{"attrs":{},"parents":[{"__entity":{"id":"T0C1","type":"Course"}}],"uid":{"__entity":{"id":"Stu7","type":"Student"}}},{"attrs":{},"parents":[{"__entity":{"id":"T0C1","type":"Course"}},{"__entity":{"id":"T0C0","type":"Course"}}],"uid":{"__entity":{"id":"Stu8","type":"Student"}}},{"attrs":{},"parents":[{"__entity":{"id":"T0C0","type":"Course"}},{"__entity":{"id":"T0C1","type":"Course"}},{"__entity":{"id":"T1C0","type":"Course"}}],"uid":{"__entity":{"id":"Stu9","type":"Student"}}},{"attrs":{},"parents":[{"__entity":{"id":"T0C0","type":"Course"}},{"__entity":{"id":"T0C1","type":"Course"}},{"__entity":{"id":"T1C0","type":"Course"}}],"uid":{"__entity":{"id":"Stu10","type":"Student"}}},{"attrs":{},"parents":[{"__entity":{"id":"T0C1","type":"Course"}},{"__entity":{"id":"T1C0","type":"Course"}},{"__entity":{"id":"T0C0","type":"Course"}}],"uid":{"__entity":{"id":"Stu11","type":"Student"}}},{"attrs":{},"parents":[{"__entity":{"id":"T0C1","type":"Course"}},{"__entity":{"id":"T1C0","type":"Course"}},{"__entity":{"id":"T0C0","type":"Course"}}],"uid":{"__entity":{"id":"Stu12","type":"Student"}}},{"attrs":{},"parents":[{"__entity":{"id":"T1C0","type":"Course"}},{"__entity":{"id":"T0C1","type":"Course"}},{"__entity":{"id":"T0C0","type":"Course"}}],"uid":{"__entity":{"id":"Stu13","type":"Student"}}},{"attrs":{},"parents":[{"__entity":{"id":"T0C0","type":"Course"}},{"__entity":{"id":"T0C1","type":"Course"}},{"__entity":{"id":"T1C0","type":"Course"}}],"uid":{"__entity":{"id":"Stu14","type":"Student"}}},{"attrs":{},"parents":[{"__entity":{"id":"T1C0","type":"Course"}},{"__entity":{"id":"T0C1","type":"Course"}},{"__entity":{"id":"T0C0","type":"Course"}}],"uid":{"__entity":{"id":"Stu15","type":"Student"}}},{"attrs":{},"parents":[{"__entity":{"id":"T0C0","type":"Course"}},{"__entity":{"id":"T0C1","type":"Course"}},{"__entity":{"id":"T1C0","type":"Course"}}],"uid":{"__entity":{"id":"Stu16","type":"Student"}}},{"attrs":{},"parents":[{"__entity":{"id":"T1C0","type":"Course"}},{"__entity":{"id":"T0C1","type":"Course"}}],"uid":{"__entity":{"id":"Stu17","type":"Student"}}},{"attrs":{},"parents":[{"__entity":{"id":"T0C1","type":"Course"}}],"uid":{"__entity":{"id":"Stu18","type":"Student"}}},{"attrs":{},"parents":[{"__entity":{"id":"T1C0","type":"Course"}},{"__entity":{"id":"T0C1","type":"Course"}},{"__entity":{"id":"T0C0","type":"Course"}}],"uid":{"__entity":{"id":"Stu19","type":"Student"}}},{"attrs":{},"parents":[{"__entity":{"id":"T2C0","type":"Course"}},{"__entity":{"id":"T0C1","type":"Course"}},{"__entity":{"id":"T1C0","type":"Course"}},{"__entity":{"id":"T0C0","type":"Course"}}],"uid":{"__entity":{"id":"Stu20","type":"Student"}}},{"attrs":{},"parents":[{"__entity":{"id":"T1C0","type":"Course"}},{"__entity":{"id":"T0C0","type":"Course"}}],"uid":{"__entity":{"id":"Stu21","type":"Student"}}},{"attrs":{},"parents":[{"__entity":{"id":"T0C0","type":"Course"}}],"uid":{"__entity":{"id":"Stu22","type":"Student"}}},{"attrs":{},"parents":[{"__entity":{"id":"T0C1","type":"Course"}},{"__entity":{"id":"T2C0","type":"Course"}},{"__entity":{"id":"T0C0","type":"Course"}},{"__entity":{"id":"T1C0","type":"Course"}}],"uid":{"__entity":{"id":"Stu23","type":"Student"}}},{"attrs":{},"parents":[{"__entity":{"id":"T0C0","type":"Course"}}],"uid":{"__entity":{"id":"Stu24","type":"Student"}}},{"attrs":{},"parents":[{"__entity":{"id":"T0C0","type":"Course"}},{"__entity":{"id":"T1C0","type":"Course"}}],"uid":{"__entity":{"id":"Stu25","type":"Student"}}},{"attrs":{},"parents":[{"__entity":{"id":"T1C0","type":"Course"}},{"__entity":{"id":"T0C1","type":"Course"}},{"__entity":{"id":"T0C0","type":"Course"}}],"uid":{"__entity":{"id":"Stu26","type":"Student"}}},{"attrs":{},"parents":[{"__entity":{"id":"T0C1","type":"Course"}},{"__entity":{"id":"T1C0","type":"Course"}},{"__entity":{"id":"T0C0","type":"Course"}}],"uid":{"__entity":{"id":"Stu27","type":"Student"}}},{"attrs":{},"parents":[{"__entity":{"id":"T0C1","type":"Course"}}],"uid":{"__entity":{"id":"Stu28","type":"Student"}}},{"attrs":{},"parents":[{"__entity":{"id":"T0C0","type":"Course"}},{"__entity":{"id":"T0C1","type":"Course"}},{"__entity":{"id":"T2C0","type":"Course"}}],"uid":{"__entity":{"id":"Stu29","type":"Student"}}},{"attrs":{},"parents":[{"__entity":{"id":"T1C0","type":"Course"}},{"__entity":{"id":"T0C1","type":"Course"}},{"__entity":{"id":"T0C0","type":"Course"}},{"__entity":{"id":"T2C0","type":"Course"}},{"__entity":{"id":"T3C0","type":"Course"}}],"uid":{"__entity":{"id":"Stu30","type":"Student"}}},{"attrs":{},"parents":[{"__entity":{"id":"T1C0","type":"Course"}},{"__entity":{"id":"T0C0","type":"Course"}},{"__entity":{"id":"T0C1","type":"Course"}},{"__entity":{"id":"T2C0","type":"Course"}}],"uid":{"__entity":{"id":"Stu31","type":"Student"}}},{"attrs":{},"parents":[{"__entity":{"id":"T2C0","type":"Course"}},{"__entity":{"id":"T3C0","type":"Course"}}],"uid":{"__entity":{"id":"Stu32","type":"Student"}}},{"attrs":{},"parents":[{"__entity":{"id":"T1C0","type":"Course"}},{"__entity":{"id":"T2C0","type":"Course"}},{"__entity":{"id":"T0C0","type":"Course"}},{"__entity":{"id":"T3C0","type":"Course"}},{"__entity":{"id":"T0C1","type":"Course"}}],"uid":{"__entity":{"id":"Stu33","type":"Student"}}},{"attrs":{},"parents":[{"__entity":{"id":"T0C0","type":"Course"}},{"__entity":{"id":"T1C0","type":"Course"}}],"uid":{"__entity":{"id":"Stu34","type":"Student"}}},{"attrs":{},"parents":[{"__entity":{"id":"T2C0","type":"Course"}},{"__entity":{"id":"T1C0","type":"Course"}},{"__entity":{"id":"T3C0","type":"Course"}}],"uid":{"__entity":{"id":"Stu35","type":"Student"}}},{"attrs":{},"parents":[{"__entity":{"id":"T3C0","type":"Course"}},{"__entity":{"id":"T0C1","type":"Course"}},{"__entity":{"id":"T2C0","type":"Course"}},{"__entity":{"id":"T1C0","type":"Course"}},{"__entity":{"id":"T0C0","type":"Course"}}],"uid":{"__entity":{"id":"Stu36","type":"Student"}}},{"attrs":{},"parents":[{"__entity":{"id":"T0C0","type":"Course"}},{"__entity":{"id":"T0C1","type":"Course"}},{"__entity":{"id":"T1C0","type":"Course"}},{"__entity":{"id":"T3C0","type":"Course"}},{"__entity":{"id":"T2C0","type":"Course"}}],"uid":{"__entity":{"id":"Stu37","type":"Student"}}},{"attrs":{},"parents":[{"__entity":{"id":"T2C0","type":"Course"}},{"__entity":{"id":"T1C0","type":"Course"}},{"__entity":{"id":"T0C0","type":"Course"}},{"__entity":{"id":"T3C0","type":"Course"}},{"__entity":{"id":"T0C1","type":"Course"}}],"uid":{"__entity":{"id":"Stu38","type":"Student"}}},{"attrs":{},"parents":[{"__entity":{"id":"T3C0","type":"Course"}}],"uid":{"__entity":{"id":"Stu39","type":"Student"}}},{"attrs":{},"parents":[{"__entity":{"id":"T0C1","type":"Course"}},{"__entity":{"id":"T1C0","type":"Course"}},{"__entity":{"id":"T0C0","type":"Course"}}],"uid":{"__entity":{"id":"Stu40","type":"Student"}}},{"attrs":{},"parents":[{"__entity":{"id":"T4C0","type":"Course"}},{"__entity":{"id":"T3C0","type":"Course"}},{"__entity":{"id":"T2C0","type":"Course"}},{"__entity":{"id":"T0C1","type":"Course"}},{"__entity":{"id":"T1C0","type":"Course"}}],"uid":{"__entity":{"id":"Stu41","type":"Student"}}},{"attrs":{},"parents":[{"__entity":{"id":"T0C0","type":"Course"}},{"__entity":{"id":"T2C0","type":"Course"}},{"__entity":{"id":"T4C0","type":"Course"}},{"__entity":{"id":"T0C1","type":"Course"}}],"uid":{"__entity":{"id":"Stu42","type":"Student"}}},{"attrs":{},"parents":[{"__entity":{"id":"T0C1","type":"Course"}}],"uid":{"__entity":{"id":"Stu43","type":"Student"}}},{"attrs":{},"parents":[{"__entity":{"id":"T3C0","type":"Course"}},{"__entity":{"id":"T2C0","type":"Course"}},{"__entity":{"id":"T0C0","type":"Course"}}],"uid":{"__entity":{"id":"Stu44","type":"Student"}}},{"attrs":{},"parents":[{"__entity":{"id":"T4C0","type":"Course"}},{"__entity":{"id":"T0C1","type":"Course"}}],"uid":{"__entity":{"id":"Stu45","type":"Student"}}},{"attrs":{},"parents":[{"__entity":{"id":"T0C1","type":"Course"}},{"__entity":{"id":"T0C0","type":"Course"}},{"__entity":{"id":"T3C0","type":"Course"}}],"uid":{"__entity":{"id":"Stu46","type":"Student"}}},{"attrs":{},"parents":[{"__entity":{"id":"T4C0","type":"Course"}}],"uid":{"__entity":{"id":"Stu47","type":"Student"}}},{"attrs":{},"parents":[{"__entity":{"id":"T0C0","type":"Course"}}],"uid":{"__entity":{"id":"Stu48","type":"Student"}}},{"attrs":{},"parents":[{"__entity":{"id":"T3C0","type":"Course"}},{"__entity":{"id":"T2C0","type":"Course"}},{"__entity":{"id":"T4C0","type":"Course"}},{"__entity":{"id":"T1C0","type":"Course"}},{"__entity":{"id":"T0C1","type":"Course"}}],"uid":{"__entity":{"id":"Stu49","type":"Student"}}},{"attrs":{"role":{"__entity":{"id":"Teacher","type":"Role"}}},"parents":[{"__entity":{"id":"T0C0","type":"Course"}},{"__entity":{"id":"T0C1","type":"Course"}}],"uid":{"__entity":{"id":"TE0","type":"Staff"}}},{"attrs":{"role":{"__entity":{"id":"Teacher","type":"Role"}}},"parents":[{"__entity":{"id":"T1C0","type":"Course"}}],"uid":{"__entity":{"id":"TE1","type":"Staff"}}},{"attrs":{"role":{"__entity":{"id":"Teacher","type":"Role"}}},"parents":[{"__entity":{"id":"T2C0","type":"Course"}}],"uid":{"__entity":{"id":"TE2","type":"Staff"}}},{"attrs":{"role":{"__entity":{"id":"Teacher","type":"Role"}}},"parents":[{"__entity":{"id":"T3C0","type":"Course"}}],"uid":{"__entity":{"id":"TE3","type":"Staff"}}},{"attrs":{"role":{"__entity":{"id":"Teacher","type":"Role"}}},"parents":[{"__entity":{"id":"T4C0","type":"Course"}}],"uid":{"__entity":{"id":"TE4","type":"Staff"}}},{"attrs":{"role":{"__entity":{"id":"TA","type":"Role"}}},"parents":[{"__entity":{"id":"T0C0","type":"Course"}}],"uid":{"__entity":{"id":"TA0","type":"Staff"}}},{"attrs":{"role":{"__entity":{"id":"TA","type":"Role"}}},"parents":[{"__entity":{"id":"T0C0","type":"Course"}},{"__entity":{"id":"T0C1","type":"Course"}}],"uid":{"__entity":{"id":"TA1","type":"Staff"}}},{"attrs":{"role":{"__entity":{"id":"TA","type":"Role"}}},"parents":[{"__entity":{"id":"T0C0","type":"Course"}},{"__entity":{"id":"T2C0","type":"Course"}}],"uid":{"__entity":{"id":"TA2","type":"Staff"}}},{"attrs":{"role":{"__entity":{"id":"TA","type":"Role"}}},"parents":[{"__entity":{"id":"T1C0","type":"Course"}},{"__entity":{"id":"T2C0","type":"Course"}}],"uid":{"__entity":{"id":"TA3","type":"Staff"}}},{"attrs":{"role":{"__entity":{"id":"TA","type":"Role"}}},"parents":[{"__entity":{"id":"T1C0","type":"Course"}},{"__entity":{"id":"T3C0","type":"Course"}}],"uid":{"__entity":{"id":"TA4","type":"Staff"}}},{"attrs":{},"parents":[],"uid":{"__entity":{"id":"T0C0","type":"Course"}}},{"attrs":{},"parents":[],"uid":{"__entity":{"id":"T0C1","type":"Course"}}},{"attrs":{},"parents":[],"uid":{"__entity":{"id":"T1C0","type":"Course"}}},{"attrs":{},"parents":[],"uid":{"__entity":{"id":"T2C0","type":"Course"}}},{"attrs":{},"parents":[],"uid":{"__entity":{"id":"T3C0","type":"Course"}}},{"attrs":{},"parents":[],"uid":{"__entity":{"id":"T4C0","type":"Course"}}},{"attrs":{"course":{"__entity":{"id":"T0C0","type":"Course"}}},"parents":[],"uid":{"__entity":{"id":"T0C0A0","type":"Assignment"}}},{"attrs":{"course":{"__entity":{"id":"T0C0","type":"Course"}}},"parents":[],"uid":{"__entity":{"id":"T0C0A1","type":"Assignment"}}},{"attrs":{"course":{"__entity":{"id":"T0C1","type":"Course"}}},"parents":[],"uid":{"__entity":{"id":"T0C1A0","type":"Assignment"}}},{"attrs":{"course":{"__entity":{"id":"T0C1","type":"Course"}}},"parents":[],"uid":{"__entity":{"id":"T0C1A1","type":"Assignment"}}},{"attrs":{"course":{"__entity":{"id":"T0C1","type":"Course"}}},"parents":[],"uid":{"__entity":{"id":"T0C1A2","type":"Assignment"}}},{"attrs":{"course":{"__entity":{"id":"T1C0","type":"Course"}}},"parents":[],"uid":{"__entity":{"id":"T1C0A0","type":"Assignment"}}},{"attrs":{"course":{"__entity":{"id":"T2C0","type":"Course"}}},"parents":[],"uid":{"__entity":{"id":"T2C0A0","type":"Assignment"}}},{"attrs":{"course":{"__entity":{"id":"T3C0","type":"Course"}}},"parents":[],"uid":{"__entity":{"id":"T3C0A0","type":"Assignment"}}},{"attrs":{"course":{"__entity":{"id":"T3C0","type":"Course"}}},"parents":[],"uid":{"__entity":{"id":"T3C0A1","type":"Assignment"}}},{"attrs":{"course":{"__entity":{"id":"T4C0","type":"Course"}}},"parents":[],"uid":{"__entity":{"id":"T4C0A0","type":"Assignment"}}},{"attrs":{"assignment":{"__entity":{"id":"T0C0A0","type":"Assignment"}},"student":{"__entity":{"id":"Stu0","type":"Student"}}},"parents":[],"uid":{"__entity":{"id":"GT0C0A0SStu0","type":"Grade"}}},{"attrs":{"assignment":{"__entity":{"id":"T0C0A1","type":"Assignment"}},"student":{"__entity":{"id":"Stu0","type":"Student"}}},"parents":[],"uid":{"__entity":{"id":"GT0C0A1SStu0","type":"Grade"}}},{"attrs":{"assignment":{"__entity":{"id":"T0C1A0","type":"Assignment"}},"student":{"__entity":{"id":"Stu0","type":"Student"}}},"parents":[],"uid":{"__entity":{"id":"GT0C1A0SStu0","type":"Grade"}}},{"attrs":{"assignment":{"__entity":{"id":"T0C1A1","type":"Assignment"}},"student":{"__entity":{"id":"Stu0","type":"Student"}}},"parents":[],"uid":{"__entity":{"id":"GT0C1A1SStu0","type":"Grade"}}},{"attrs":{"assignment":{"__entity":{"id":"T0C1A2","type":"Assignment"}},"student":{"__entity":{"id":"Stu0","type":"Student"}}},"parents":[],"uid":{"__entity":{"id":"GT0C1A2SStu0","type":"Grade"}}},{"attrs":{"assignment":{"__entity":{"id":"T1C0A0","type":"Assignment"}},"student":{"__entity":{"id":"Stu0","type":"Student"}}},"parents":[],"uid":{"__entity":{"id":"GT1C0A0SStu0","type":"Grade"}}},{"attrs":{"assignment":{"__entity":{"id":"T0C0A0","type":"Assignment"}},"student":{"__entity":{"id":"Stu1","type":"Student"}}},"parents":[],"uid":{"__entity":{"id":"GT0C0A0SStu1","type":"Grade"}}},{"attrs":{"assignment":{"__entity":{"id":"T0C0A1","type":"Assignment"}},"student":{"__entity":{"id":"Stu1","type":"Student"}}},"parents":[],"uid":{"__entity":{"id":"GT0C0A1SStu1","type":"Grade"}}},{"attrs":{"assignment":{"__entity":{"id":"T0C1A0","type":"Assignment"}},"student":{"__entity":{"id":"Stu2","type":"Student"}}},"parents":[],"uid":{"__entity":{"id":"GT0C1A0SStu2","type":"Grade"}}},{"attrs":{"assignment":{"__entity":{"id":"T0C1A1","type":"Assignment"}},"student":{"__entity":{"id":"Stu2","type":"Student"}}},"parents":[],"uid":{"__entity":{"id":"GT0C1A1SStu2","type":"Grade"}}},{"attrs":{"assignment":{"__entity":{"id":"T0C1A2","type":"Assignment"}},"student":{"__entity":{"id":"Stu2","type":"Student"}}},"parents":[],"uid":{"__entity":{"id":"GT0C1A2SStu2","type":"Grade"}}},{"attrs":{"assignment":{"__entity":{"id":"T0C0A0","type":"Assignment"}},"student":{"__entity":{"id":"Stu3","type":"Student"}}},"parents":[],"uid":{"__entity":{"id":"GT0C0A0SStu3","type":"Grade"}}},{"attrs":{"assignment":{"__entity":{"id":"T0C0A1","type":"Assignment"}},"student":{"__entity":{"id":"Stu3","type":"Student"}}},"parents":[],"uid":{"__entity":{"id":"GT0C0A1SStu3","type":"Grade"}}},{"attrs":{"assignment":{"__entity":{"id":"T0C1A0","type":"Assignment"}},"student":{"__entity":{"id":"Stu3","type":"Student"}}},"parents":[],"uid":{"__entity":{"id":"GT0C1A0SStu3","type":"Grade"}}},{"attrs":{"assignment":{"__entity":{"id":"T0C1A1","type":"Assignment"}},"student":{"__entity":{"id":"Stu3","type":"Student"}}},"parents":[],"uid":{"__entity":{"id":"GT0C1A1SStu3","type":"Grade"}}},{"attrs":{"assignment":{"__entity":{"id":"T0C1A2","type":"Assignment"}},"student":{"__entity":{"id":"Stu3","type":"Student"}}},"parents":[],"uid":{"__entity":{"id":"GT0C1A2SStu3","type":"Grade"}}},{"attrs":{"assignment":{"__entity":{"id":"T1C0A0","type":"Assignment"}},"student":{"__entity":{"id":"Stu3","type":"Student"}}},"parents":[],"uid":{"__entity":{"id":"GT1C0A0SStu3","type":"Grade"}}},{"attrs":{"assignment":{"__entity":{"id":"T0C0A0","type":"Assignment"}},"student":{"__entity":{"id":"Stu4","type":"Student"}}},"parents":[],"uid":{"__entity":{"id":"GT0C0A0SStu4","type":"Grade"}}},{"attrs":{"assignment":{"__entity":{"id":"T0C0A1","type":"Assignment"}},"student":{"__entity":{"id":"Stu4","type":"Student"}}},"parents":[],"uid":{"__entity":{"id":"GT0C0A1SStu4","type":"Grade"}}},{"attrs":{"assignment":{"__entity":{"id":"T0C1A0","type":"Assignment"}},"student":{"__entity":{"id":"Stu4","type":"Student"}}},"parents":[],"uid":{"__entity":{"id":"GT0C1A0SStu4","type":"Grade"}}},{"attrs":{"assignment":{"__entity":{"id":"T0C1A1","type":"Assignment"}},"student":{"__entity":{"id":"Stu4","type":"Student"}}},"parents":[],"uid":{"__entity":{"id":"GT0C1A1SStu4","type":"Grade"}}},{"attrs":{"assignment":{"__entity":{"id":"T0C1A2","type":"Assignment"}},"student":{"__entity":{"id":"Stu4","type":"Student"}}},"parents":[],"uid":{"__entity":{"id":"GT0C1A2SStu4","type":"Grade"}}},{"attrs":{"assignment":{"__entity":{"id":"T1C0A0","type":"Assignment"}},"student":{"__entity":{"id":"Stu4","type":"Student"}}},"parents":[],"uid":{"__entity":{"id":"GT1C0A0SStu4","type":"Grade"}}},{"attrs":{"assignment":{"__entity":{"id":"T0C0A0","type":"Assignment"}},"student":{"__entity":{"id":"Stu5","type":"Student"}}},"parents":[],"uid":{"__entity":{"id":"GT0C0A0SStu5","type":"Grade"}}},{"attrs":{"assignment":{"__entity":{"id":"T0C0A1","type":"Assignment"}},"student":{"__entity":{"id":"Stu5","type":"Student"}}},"parents":[],"uid":{"__entity":{"id":"GT0C0A1SStu5","type":"Grade"}}},{"attrs":{"assignment":{"__entity":{"id":"T0C1A0","type":"Assignment"}},"student":{"__entity":{"id":"Stu5","type":"Student"}}},"parents":[],"uid":{"__entity":{"id":"GT0C1A0SStu5","type":"Grade"}}},{"attrs":{"assignment":{"__entity":{"id":"T0C1A1","type":"Assignment"}},"student":{"__entity":{"id":"Stu5","type":"Student"}}},"parents":[],"uid":{"__entity":{"id":"GT0C1A1SStu5","type":"Grade"}}},{"attrs":{"assignment":{"__entity":{"id":"T0C1A2","type":"Assignment"}},"student":{"__entity":{"id":"Stu5","type":"Student"}}},"parents":[],"uid":{"__entity":{"id":"GT0C1A2SStu5","type":"Grade"}}},{"attrs":{"assignment":{"__entity":{"id":"T1C0A0","type":"Assignment"}},"student":{"__entity":{"id":"Stu5","type":"Student"}}},"parents":[],"uid":{"__entity":{"id":"GT1C0A0SStu5","type":"Grade"}}},{"attrs":{"assignment":{"__entity":{"id":"T0C0A0","type":"Assignment"}},"student":{"__entity":{"id":"Stu6","type":"Student"}}},"parents":[],"uid":{"__entity":{"id":"GT0C0A0SStu6","type":"Grade"}}},{"attrs":{"assignment":{"__entity":{"id":"T0C0A1","type":"Assignment"}},"student":{"__entity":{"id":"Stu6","type":"Student"}}},"parents":[],"uid":{"__entity":{"id":"GT0C0A1SStu6","type":"Grade"}}},{"attrs":{"assignment":{"__entity":{"id":"T0C1A0","type":"Assignment"}},"student":{"__entity":{"id":"Stu6","type":"Student"}}},"parents":[],"uid":{"__entity":{"id":"GT0C1A0SStu6","type":"Grade"}}},{"attrs":{"assignment":{"__entity":{"id":"T0C1A1","type":"Assignment"}},"student":{"__entity":{"id":"Stu6","type":"Student"}}},"parents":[],"uid":{"__entity":{"id":"GT0C1A1SStu6","type":"Grade"}}},{"attrs":{"assignment":{"__entity":{"id":"T0C1A2","type":"Assignment"}},"student":{"__entity":{"id":"Stu6","type":"Student"}}},"parents":[],"uid":{"__entity":{"id":"GT0C1A2SStu6","type":"Grade"}}},{"attrs":{"assignment":{"__entity":{"id":"T0C1A0","type":"Assignment"}},"student":{"__entity":{"id":"Stu7","type":"Student"}}},"parents":[],"uid":{"__entity":{"id":"GT0C1A0SStu7","type":"Grade"}}},{"attrs":{"assignment":{"__entity":{"id":"T0C1A1","type":"Assignment"}},"student":{"__entity":{"id":"Stu7","type":"Student"}}},"parents":[],"uid":{"__entity":{"id":"GT0C1A1SStu7","type":"Grade"}}},{"attrs":{"assignment":{"__entity":{"id":"T0C1A2","type":"Assignment"}},"student":{"__entity":{"id":"Stu7","type":"Student"}}},"parents":[],"uid":{"__entity":{"id":"GT0C1A2SStu7","type":"Grade"}}},{"attrs":{"assignment":{"__entity":{"id":"T0C0A0","type":"Assignment"}},"student":{"__entity":{"id":"Stu8","type":"Student"}}},"parents":[],"uid":{"__entity":{"id":"GT0C0A0SStu8","type":"Grade"}}},{"attrs":{"assignment":{"__entity":{"id":"T0C0A1","type":"Assignment"}},"student":{"__entity":{"id":"Stu8","type":"Student"}}},"parents":[],"uid":{"__entity":{"id":"GT0C0A1SStu8","type":"Grade"}}},{"attrs":{"assignment":{"__entity":{"id":"T0C1A0","type":"Assignment"}},"student":{"__entity":{"id":"Stu8","type":"Student"}}},"parents":[],"uid":{"__entity":{"id":"GT0C1A0SStu8","type":"Grade"}}},{"attrs":{"assignment":{"__entity":{"id":"T0C1A1","type":"Assignment"}},"student":{"__entity":{"id":"Stu8","type":"Student"}}},"parents":[],"uid":{"__entity":{"id":"GT0C1A1SStu8","type":"Grade"}}},{"attrs":{"assignment":{"__entity":{"id":"T0C1A2","type":"Assignment"}},"student":{"__entity":{"id":"Stu8","type":"Student"}}},"parents":[],"uid":{"__entity":{"id":"GT0C1A2SStu8","type":"Grade"}}},{"attrs":{"assignment":{"__entity":{"id":"T0C0A0","type":"Assignment"}},"student":{"__entity":{"id":"Stu9","type":"Student"}}},"parents":[],"uid":{"__entity":{"id":"GT0C0A0SStu9","type":"Grade"}}},{"attrs":{"assignment":{"__entity":{"id":"T0C0A1","type":"Assignment"}},"student":{"__entity":{"id":"Stu9","type":"Student"}}},"parents":[],"uid":{"__entity":{"id":"GT0C0A1SStu9","type":"Grade"}}},{"attrs":{"assignment":{"__entity":{"id":"T0C1A0","type":"Assignment"}},"student":{"__entity":{"id":"Stu9","type":"Student"}}},"parents":[],"uid":{"__entity":{"id":"GT0C1A0SStu9","type":"Grade"}}},{"attrs":{"assignment":{"__entity":{"id":"T0C1A1","type":"Assignment"}},"student":{"__entity":{"id":"Stu9","type":"Student"}}},"parents":[],"uid":{"__entity":{"id":"GT0C1A1SStu9","type":"Grade"}}},{"attrs":{"assignment":{"__entity":{"id":"T0C1A2","type":"Assignment"}},"student":{"__entity":{"id":"Stu9","type":"Student"}}},"parents":[],"uid":{"__entity":{"id":"GT0C1A2SStu9","type":"Grade"}}},{"attrs":{"assignment":{"__entity":{"id":"T1C0A0","type":"Assignment"}},"student":{"__entity":{"id":"Stu9","type":"Student"}}},"parents":[],"uid":{"__entity":{"id":"GT1C0A0SStu9","type":"Grade"}}},{"attrs":{"assignment":{"__entity":{"id":"T0C0A0","type":"Assignment"}},"student":{"__entity":{"id":"Stu10","type":"Student"}}},"parents":[],"uid":{"__entity":{"id":"GT0C0A0SStu10","type":"Grade"}}},{"attrs":{"assignment":{"__entity":{"id":"T0C0A1","type":"Assignment"}},"student":{"__entity":{"id":"Stu10","type":"Student"}}},"parents":[],"uid":{"__entity":{"id":"GT0C0A1SStu10","type":"Grade"}}},{"attrs":{"assignment":{"__entity":{"id":"T0C1A0","type":"Assignment"}},"student":{"__entity":{"id":"Stu10","type":"Student"}}},"parents":[],"uid":{"__entity":{"id":"GT0C1A0SStu10","type":"Grade"}}},{"attrs":{"assignment":{"__entity":{"id":"T0C1A1","type":"Assignment"}},"student":{"__entity":{"id":"Stu10","type":"Student"}}},"parents":[],"uid":{"__entity":{"id":"GT0C1A1SStu10","type":"Grade"}}},{"attrs":{"assignment":{"__entity":{"id":"T0C1A2","type":"Assignment"}},"student":{"__entity":{"id":"Stu10","type":"Student"}}},"parents":[],"uid":{"__entity":{"id":"GT0C1A2SStu10","type":"Grade"}}},{"attrs":{"assignment":{"__entity":{"id":"T1C0A0","type":"Assignment"}},"student":{"__entity":{"id":"Stu10","type":"Student"}}},"parents":[],"uid":{"__entity":{"id":"GT1C0A0SStu10","type":"Grade"}}},{"attrs":{"assignment":{"__entity":{"id":"T0C0A0","type":"Assignment"}},"student":{"__entity":{"id":"Stu11","type":"Student"}}},"parents":[],"uid":{"__entity":{"id":"GT0C0A0SStu11","type":"Grade"}}},{"attrs":{"assignment":{"__entity":{"id":"T0C0A1","type":"Assignment"}},"student":{"__entity":{"id":"Stu11","type":"Student"}}},"parents":[],"uid":{"__entity":{"id":"GT0C0A1SStu11","type":"Grade"}}},{"attrs":{"assignment":{"__entity":{"id":"T0C1A0","type":"Assignment"}},"student":{"__entity":{"id":"Stu11","type":"Student"}}},"parents":[],"uid":{"__entity":{"id":"GT0C1A0SStu11","type":"Grade"}}},{"attrs":{"assignment":{"__entity":{"id":"T0C1A1","type":"Assignment"}},"student":{"__entity":{"id":"Stu11","type":"Student"}}},"parents":[],"uid":{"__entity":{"id":"GT0C1A1SStu11","type":"Grade"}}},{"attrs":{"assignment":{"__entity":{"id":"T0C1A2","type":"Assignment"}},"student":{"__entity":{"id":"Stu11","type":"Student"}}},"parents":[],"uid":{"__entity":{"id":"GT0C1A2SStu11","type":"Grade"}}},{"attrs":{"assignment":{"__entity":{"id":"T1C0A0","type":"Assignment"}},"student":{"__entity":{"id":"Stu11","type":"Student"}}},"parents":[],"uid":{"__entity":{"id":"GT1C0A0SStu11","type":"Grade"}}},{"attrs":{"assignment":{"__entity":{"id":"T0C0A0","type":"Assignment"}},"student":{"__entity":{"id":"Stu12","type":"Student"}}},"parents":[],"uid":{"__entity":{"id":"GT0C0A0SStu12","type":"Grade"}}},{"attrs":{"assignment":{"__entity":{"id":"T0C0A1","type":"Assignment"}},"student":{"__entity":{"id":"Stu12","type":"Student"}}},"parents":[],"uid":{"__entity":{"id":"GT0C0A1SStu12","type":"Grade"}}},{"attrs":{"assignment":{"__entity":{"id":"T0C1A0","type":"Assignment"}},"student":{"__entity":{"id":"Stu12","type":"Student"}}},"parents":[],"uid":{"__entity":{"id":"GT0C1A0SStu12","type":"Grade"}}},{"attrs":{"assignment":{"__entity":{"id":"T0C1A1","type":"Assignment"}},"student":{"__entity":{"id":"Stu12","type":"Student"}}},"parents":[],"uid":{"__entity":{"id":"GT0C1A1SStu12","type":"Grade"}}},{"attrs":{"assignment":{"__entity":{"id":"T0C1A2","type":"Assignment"}},"student":{"__entity":{"id":"Stu12","type":"Student"}}},"parents":[],"uid":{"__entity":{"id":"GT0C1A2SStu12","type":"Grade"}}},{"attrs":{"assignment":{"__entity":{"id":"T1C0A0","type":"Assignment"}},"student":{"__entity":{"id":"Stu12","type":"Student"}}},"parents":[],"uid":{"__entity":{"id":"GT1C0A0SStu12","type":"Grade"}}},{"attrs":{"assignment":{"__entity":{"id":"T0C0A0","type":"Assignment"}},"student":{"__entity":{"id":"Stu13","type":"Student"}}},"parents":[],"uid":{"__entity":{"id":"GT0C0A0SStu13","type":"Grade"}}},{"attrs":{"assignment":{"__entity":{"id":"T0C0A1","type":"Assignment"}},"student":{"__entity":{"id":"Stu13","type":"Student"}}},"parents":[],"uid":{"__entity":{"id":"GT0C0A1SStu13","type":"Grade"}}},{"attrs":{"assignment":{"__entity":{"id":"T0C1A0","type":"Assignment"}},"student":{"__entity":{"id":"Stu13","type":"Student"}}},"parents":[],"uid":{"__entity":{"id":"GT0C1A0SStu13","type":"Grade"}}},{"attrs":{"assignment":{"__entity":{"id":"T0C1A1","type":"Assignment"}},"student":{"__entity":{"id":"Stu13","type":"Student"}}},"parents":[],"uid":{"__entity":{"id":"GT0C1A1SStu13","type":"Grade"}}},{"attrs":{"assignment":{"__entity":{"id":"T0C1A2","type":"Assignment"}},"student":{"__entity":{"id":"Stu13","type":"Student"}}},"parents":[],"uid":{"__entity":{"id":"GT0C1A2SStu13","type":"Grade"}}},{"attrs":{"assignment":{"__entity":{"id":"T1C0A0","type":"Assignment"}},"student":{"__entity":{"id":"Stu13","type":"Student"}}},"parents":[],"uid":{"__entity":{"id":"GT1C0A0SStu13","type":"Grade"}}},{"attrs":{"assignment":{"__entity":{"id":"T0C0A0","type":"Assignment"}},"student":{"__entity":{"id":"Stu14","type":"Student"}}},"parents":[],"uid":{"__entity":{"id":"GT0C0A0SStu14","type":"Grade"}}},{"attrs":{"assignment":{"__entity":{"id":"T0C0A1","type":"Assignment"}},"student":{"__entity":{"id":"Stu14","type":"Student"}}},"parents":[],"uid":{"__entity":{"id":"GT0C0A1SStu14","type":"Grade"}}},{"attrs":{"assignment":{"__entity":{"id":"T0C1A0","type":"Assignment"}},"student":{"__entity":{"id":"Stu14","type":"Student"}}},"parents":[],"uid":{"__entity":{"id":"GT0C1A0SStu14","type":"Grade"}}},{"attrs":{"assignment":{"__entity":{"id":"T0C1A1","type":"Assignment"}},"student":{"__entity":{"id":"Stu14","type":"Student"}}},"parents":[],"uid":{"__entity":{"id":"GT0C1A1SStu14","type":"Grade"}}},{"attrs":{"assignment":{"__entity":{"id":"T0C1A2","type":"Assignment"}},"student":{"__entity":{"id":"Stu14","type":"Student"}}},"parents":[],"uid":{"__entity":{"id":"GT0C1A2SStu14","type":"Grade"}}},{"attrs":{"assignment":{"__entity":{"id":"T1C0A0","type":"Assignment"}},"student":{"__entity":{"id":"Stu14","type":"Student"}}},"parents":[],"uid":{"__entity":{"id":"GT1C0A0SStu14","type":"Grade"}}},{"attrs":{"assignment":{"__entity":{"id":"T0C0A0","type":"Assignment"}},"student":{"__entity":{"id":"Stu15","type":"Student"}}},"parents":[],"uid":{"__entity":{"id":"GT0C0A0SStu15","type":"Grade"}}},{"attrs":{"assignment":{"__entity":{"id":"T0C0A1","type":"Assignment"}},"student":{"__entity":{"id":"Stu15","type":"Student"}}},"parents":[],"uid":{"__entity":{"id":"GT0C0A1SStu15","type":"Grade"}}},{"attrs":{"assignment":{"__entity":{"id":"T0C1A0","type":"Assignment"}},"student":{"__entity":{"id":"Stu15","type":"Student"}}},"parents":[],"uid":{"__entity":{"id":"GT0C1A0SStu15","type":"Grade"}}},{"attrs":{"assignment":{"__entity":{"id":"T0C1A1","type":"Assignment"}},"student":{"__entity":{"id":"Stu15","type":"Student"}}},"parents":[],"uid":{"__entity":{"id":"GT0C1A1SStu15","type":"Grade"}}},{"attrs":{"assignment":{"__entity":{"id":"T0C1A2","type":"Assignment"}},"student":{"__entity":{"id":"Stu15","type":"Student"}}},"parents":[],"uid":{"__entity":{"id":"GT0C1A2SStu15","type":"Grade"}}},{"attrs":{"assignment":{"__entity":{"id":"T1C0A0","type":"Assignment"}},"student":{"__entity":{"id":"Stu15","type":"Student"}}},"parents":[],"uid":{"__entity":{"id":"GT1C0A0SStu15","type":"Grade"}}},{"attrs":{"assignment":{"__entity":{"id":"T0C0A0","type":"Assignment"}},"student":{"__entity":{"id":"Stu16","type":"Student"}}},"parents":[],"uid":{"__entity":{"id":"GT0C0A0SStu16","type":"Grade"}}},{"attrs":{"assignment":{"__entity":{"id":"T0C0A1","type":"Assignment"}},"student":{"__entity":{"id":"Stu16","type":"Student"}}},"parents":[],"uid":{"__entity":{"id":"GT0C0A1SStu16","type":"Grade"}}},{"attrs":{"assignment":{"__entity":{"id":"T0C1A0","type":"Assignment"}},"student":{"__entity":{"id":"Stu16","type":"Student"}}},"parents":[],"uid":{"__entity":{"id":"GT0C1A0SStu16","type":"Grade"}}},{"attrs":{"assignment":{"__entity":{"id":"T0C1A1","type":"Assignment"}},"student":{"__entity":{"id":"Stu16","type":"Student"}}},"parents":[],"uid":{"__entity":{"id":"GT0C1A1SStu16","type":"Grade"}}},{"attrs":{"assignment":{"__entity":{"id":"T0C1A2","type":"Assignment"}},"student":{"__entity":{"id":"Stu16","type":"Student"}}},"parents":[],"uid":{"__entity":{"id":"GT0C1A2SStu16","type":"Grade"}}},{"attrs":{"assignment":{"__entity":{"id":"T1C0A0","type":"Assignment"}},"student":{"__entity":{"id":"Stu16","type":"Student"}}},"parents":[],"uid":{"__entity":{"id":"GT1C0A0SStu16","type":"Grade"}}},{"attrs":{"assignment":{"__entity":{"id":"T0C1A0","type":"Assignment"}},"student":{"__entity":{"id":"Stu17","type":"Student"}}},"parents":[],"uid":{"__entity":{"id":"GT0C1A0SStu17","type":"Grade"}}},{"attrs":{"assignment":{"__entity":{"id":"T0C1A1","type":"Assignment"}},"student":{"__entity":{"id":"Stu17","type":"Student"}}},"parents":[],"uid":{"__entity":{"id":"GT0C1A1SStu17","type":"Grade"}}},{"attrs":{"assignment":{"__entity":{"id":"T0C1A2","type":"Assignment"}},"student":{"__entity":{"id":"Stu17","type":"Student"}}},"parents":[],"uid":{"__entity":{"id":"GT0C1A2SStu17","type":"Grade"}}},{"attrs":{"assignment":{"__entity":{"id":"T1C0A0","type":"Assignment"}},"student":{"__entity":{"id":"Stu17","type":"Student"}}},"parents":[],"uid":{"__entity":{"id":"GT1C0A0SStu17","type":"Grade"}}},{"attrs":{"assignment":{"__entity":{"id":"T0C1A0","type":"Assignment"}},"student":{"__entity":{"id":"Stu18","type":"Student"}}},"parents":[],"uid":{"__entity":{"id":"GT0C1A0SStu18","type":"Grade"}}},{"attrs":{"assignment":{"__entity":{"id":"T0C1A1","type":"Assignment"}},"student":{"__entity":{"id":"Stu18","type":"Student"}}},"parents":[],"uid":{"__entity":{"id":"GT0C1A1SStu18","type":"Grade"}}},{"attrs":{"assignment":{"__entity":{"id":"T0C1A2","type":"Assignment"}},"student":{"__entity":{"id":"Stu18","type":"Student"}}},"parents":[],"uid":{"__entity":{"id":"GT0C1A2SStu18","type":"Grade"}}},{"attrs":{"assignment":{"__entity":{"id":"T0C0A0","type":"Assignment"}},"student":{"__entity":{"id":"Stu19","type":"Student"}}},"parents":[],"uid":{"__entity":{"id":"GT0C0A0SStu19","type":"Grade"}}},{"attrs":{"assignment":{"__entity":{"id":"T0C0A1","type":"Assignment"}},"student":{"__entity":{"id":"Stu19","type":"Student"}}},"parents":[],"uid":{"__entity":{"id":"GT0C0A1SStu19","type":"Grade"}}},{"attrs":{"assignment":{"__entity":{"id":"T0C1A0","type":"Assignment"}},"student":{"__entity":{"id":"Stu19","type":"Student"}}},"parents":[],"uid":{"__entity":{"id":"GT0C1A0SStu19","type":"Grade"}}},{"attrs":{"assignment":{"__entity":{"id":"T0C1A1","type":"Assignment"}},"student":{"__entity":{"id":"Stu19","type":"Student"}}},"parents":[],"uid":{"__entity":{"id":"GT0C1A1SStu19","type":"Grade"}}},{"attrs":{"assignment":{"__entity":{"id":"T0C1A2","type":"Assignment"}},"student":{"__entity":{"id":"Stu19","type":"Student"}}},"parents":[],"uid":{"__entity":{"id":"GT0C1A2SStu19","type":"Grade"}}},{"attrs":{"assignment":{"__entity":{"id":"T1C0A0","type":"Assignment"}},"student":{"__entity":{"id":"Stu19","type":"Student"}}},"parents":[],"uid":{"__entity":{"id":"GT1C0A0SStu19","type":"Grade"}}},{"attrs":{"assignment":{"__entity":{"id":"T0C0A0","type":"Assignment"}},"student":{"__entity":{"id":"Stu20","type":"Student"}}},"parents":[],"uid":{"__entity":{"id":"GT0C0A0SStu20","type":"Grade"}}},{"attrs":{"assignment":{"__entity":{"id":"T0C0A1","type":"Assignment"}},"student":{"__entity":{"id":"Stu20","type":"Student"}}},"parents":[],"uid":{"__entity":{"id":"GT0C0A1SStu20","type":"Grade"}}},{"attrs":{"assignment":{"__entity":{"id":"T0C1A0","type":"Assignment"}},"student":{"__entity":{"id":"Stu20","type":"Student"}}},"parents":[],"uid":{"__entity":{"id":"GT0C1A0SStu20","type":"Grade"}}},{"attrs":{"assignment":{"__entity":{"id":"T0C1A1","type":"Assignment"}},"student":{"__entity":{"id":"Stu20","type":"Student"}}},"parents":[],"uid":{"__entity":{"id":"GT0C1A1SStu20","type":"Grade"}}},{"attrs":{"assignment":{"__entity":{"id":"T0C1A2","type":"Assignment"}},"student":{"__entity":{"id":"Stu20","type":"Student"}}},"parents":[],"uid":{"__entity":{"id":"GT0C1A2SStu20","type":"Grade"}}},{"attrs":{"assignment":{"__entity":{"id":"T1C0A0","type":"Assignment"}},"student":{"__entity":{"id":"Stu20","type":"Student"}}},"parents":[],"uid":{"__entity":{"id":"GT1C0A0SStu20","type":"Grade"}}},{"attrs":{"assignment":{"__entity":{"id":"T2C0A0","type":"Assignment"}},"student":{"__entity":{"id":"Stu20","type":"Student"}}},"parents":[],"uid":{"__entity":{"id":"GT2C0A0SStu20","type":"Grade"}}},{"attrs":{"assignment":{"__entity":{"id":"T0C0A0","type":"Assignment"}},"student":{"__entity":{"id":"Stu21","type":"Student"}}},"parents":[],"uid":{"__entity":{"id":"GT0C0A0SStu21","type":"Grade"}}},{"attrs":{"assignment":{"__entity":{"id":"T0C0A1","type":"Assignment"}},"student":{"__entity":{"id":"Stu21","type":"Student"}}},"parents":[],"uid":{"__entity":{"id":"GT0C0A1SStu21","type":"Grade"}}},{"attrs":{"assignment":{"__entity":{"id":"T1C0A0","type":"Assignment"}},"student":{"__entity":{"id":"Stu21","type":"Student"}}},"parents":[],"uid":{"__entity":{"id":"GT1C0A0SStu21","type":"Grade"}}},{"attrs":{"assignment":{"__entity":{"id":"T0C0A0","type":"Assignment"}},"student":{"__entity":{"id":"Stu22","type":"Student"}}},"parents":[],"uid":{"__entity":{"id":"GT0C0A0SStu22","type":"Grade"}}},{"attrs":{"assignment":{"__entity":{"id":"T0C0A1","type":"Assignment"}},"student":{"__entity":{"id":"Stu22","type":"Student"}}},"parents":[],"uid":{"__entity":{"id":"GT0C0A1SStu22","type":"Grade"}}},{"attrs":{"assignment":{"__entity":{"id":"T0C0A0","type":"Assignment"}},"student":{"__entity":{"id":"Stu23","type":"Student"}}},"parents":[],"uid":{"__entity":{"id":"GT0C0A0SStu23","type":"Grade"}}},{"attrs":{"assignment":{"__entity":{"id":"T0C0A1","type":"Assignment"}},"student":{"__entity":{"id":"Stu23","type":"Student"}}},"parents":[],"uid":{"__entity":{"id":"GT0C0A1SStu23","type":"Grade"}}},{"attrs":{"assignment":{"__entity":{"id":"T0C1A0","type":"Assignment"}},"student":{"__entity":{"id":"Stu23","type":"Student"}}},"parents":[],"uid":{"__entity":{"id":"GT0C1A0SStu23","type":"Grade"}}},{"attrs":{"assignment":{"__entity":{"id":"T0C1A1","type":"Assignment"}},"student":{"__entity":{"id":"Stu23","type":"Student"}}},"parents":[],"uid":{"__entity":{"id":"GT0C1A1SStu23","type":"Grade"}}},{"attrs":{"assignment":{"__entity":{"id":"T0C1A2","type":"Assignment"}},"student":{"__entity":{"id":"Stu23","type":"Student"}}},"parents":[],"uid":{"__entity":{"id":"GT0C1A2SStu23","type":"Grade"}}},{"attrs":{"assignment":{"__entity":{"id":"T1C0A0","type":"Assignment"}},"student":{"__entity":{"id":"Stu23","type":"Student"}}},"parents":[],"uid":{"__entity":{"id":"GT1C0A0SStu23","type":"Grade"}}},{"attrs":{"assignment":{"__entity":{"id":"T2C0A0","type":"Assignment"}},"student":{"__entity":{"id":"Stu23","type":"Student"}}},"parents":[],"uid":{"__entity":{"id":"GT2C0A0SStu23","type":"Grade"}}},{"attrs":{"assignment":{"__entity":{"id":"T0C0A0","type":"Assignment"}},"student":{"__entity":{"id":"Stu24","type":"Student"}}},"parents":[],"uid":{"__entity":{"id":"GT0C0A0SStu24","type":"Grade"}}},{"attrs":{"assignment":{"__entity":{"id":"T0C0A1","type":"Assignment"}},"student":{"__entity":{"id":"Stu24","type":"Student"}}},"parents":[],"uid":{"__entity":{"id":"GT0C0A1SStu24","type":"Grade"}}},{"attrs":{"assignment":{"__entity":{"id":"T0C0A0","type":"Assignment"}},"student":{"__entity":{"id":"Stu25","type":"Student"}}},"parents":[],"uid":{"__entity":{"id":"GT0C0A0SStu25","type":"Grade"}}},{"attrs":{"assignment":{"__entity":{"id":"T0C0A1","type":"Assignment"}},"student":{"__entity":{"id":"Stu25","type":"Student"}}},"parents":[],"uid":{"__entity":{"id":"GT0C0A1SStu25","type":"Grade"}}},{"attrs":{"assignment":{"__entity":{"id":"T1C0A0","type":"Assignment"}},"student":{"__entity":{"id":"Stu25","type":"Student"}}},"parents":[],"uid":{"__entity":{"id":"GT1C0A0SStu25","type":"Grade"}}},{"attrs":{"assignment":{"__entity":{"id":"T0C0A0","type":"Assignment"}},"student":{"__entity":{"id":"Stu26","type":"Student"}}},"parents":[],"uid":{"__entity":{"id":"GT0C0A0SStu26","type":"Grade"}}},{"attrs":{"assignment":{"__entity":{"id":"T0C0A1","type":"Assignment"}},"student":{"__entity":{"id":"Stu26","type":"Student"}}},"parents":[],"uid":{"__entity":{"id":"GT0C0A1SStu26","type":"Grade"}}},{"attrs":{"assignment":{"__entity":{"id":"T0C1A0","type":"Assignment"}},"student":{"__entity":{"id":"Stu26","type":"Student"}}},"parents":[],"uid":{"__entity":{"id":"GT0C1A0SStu26","type":"Grade"}}},{"attrs":{"assignment":{"__entity":{"id":"T0C1A1","type":"Assignment"}},"student":{"__entity":{"id":"Stu26","type":"Student"}}},"parents":[],"uid":{"__entity":{"id":"GT0C1A1SStu26","type":"Grade"}}},{"attrs":{"assignment":{"__entity":{"id":"T0C1A2","type":"Assignment"}},"student":{"__entity":{"id":"Stu26","type":"Student"}}},"parents":[],"uid":{"__entity":{"id":"GT0C1A2SStu26","type":"Grade"}}},{"attrs":{"assignment":{"__entity":{"id":"T1C0A0","type":"Assignment"}},"student":{"__entity":{"id":"Stu26","type":"Student"}}},"parents":[],"uid":{"__entity":{"id":"GT1C0A0SStu26","type":"Grade"}}},{"attrs":{"assignment":{"__entity":{"id":"T0C0A0","type":"Assignment"}},"student":{"__entity":{"id":"Stu27","type":"Student"}}},"parents":[],"uid":{"__entity":{"id":"GT0C0A0SStu27","type":"Grade"}}},{"attrs":{"assignment":{"__entity":{"id":"T0C0A1","type":"Assignment"}},"student":{"__entity":{"id":"Stu27","type":"Student"}}},"parents":[],"uid":{"__entity":{"id":"GT0C0A1SStu27","type":"Grade"}}},{"attrs":{"assignment":{"__entity":{"id":"T0C1A0","type":"Assignment"}},"student":{"__entity":{"id":"Stu27","type":"Student"}}},"parents":[],"uid":{"__entity":{"id":"GT0C1A0SStu27","type":"Grade"}}},{"attrs":{"assignment":{"__entity":{"id":"T0C1A1","type":"Assignment"}},"student":{"__entity":{"id":"Stu27","type":"Student"}}},"parents":[],"uid":{"__entity":{"id":"GT0C1A1SStu27","type":"Grade"}}},{"attrs":{"assignment":{"__entity":{"id":"T0C1A2","type":"Assignment"}},"student":{"__entity":{"id":"Stu27","type":"Student"}}},"parents":[],"uid":{"__entity":{"id":"GT0C1A2SStu27","type":"Grade"}}},{"attrs":{"assignment":{"__entity":{"id":"T1C0A0","type":"Assignment"}},"student":{"__entity":{"id":"Stu27","type":"Student"}}},"parents":[],"uid":{"__entity":{"id":"GT1C0A0SStu27","type":"Grade"}}},{"attrs":{"assignment":{"__entity":{"id":"T0C1A0","type":"Assignment"}},"student":{"__entity":{"id":"Stu28","type":"Student"}}},"parents":[],"uid":{"__entity":{"id":"GT0C1A0SStu28","type":"Grade"}}},{"attrs":{"assignment":{"__entity":{"id":"T0C1A1","type":"Assignment"}},"student":{"__entity":{"id":"Stu28","type":"Student"}}},"parents":[],"uid":{"__entity":{"id":"GT0C1A1SStu28","type":"Grade"}}},{"attrs":{"assignment":{"__entity":{"id":"T0C1A2","type":"Assignment"}},"student":{"__entity":{"id":"Stu28","type":"Student"}}},"parents":[],"uid":{"__entity":{"id":"GT0C1A2SStu28","type":"Grade"}}},{"attrs":{"assignment":{"__entity":{"id":"T0C0A0","type":"Assignment"}},"student":{"__entity":{"id":"Stu29","type":"Student"}}},"parents":[],"uid":{"__entity":{"id":"GT0C0A0SStu29","type":"Grade"}}},{"attrs":{"assignment":{"__entity":{"id":"T0C0A1","type":"Assignment"}},"student":{"__entity":{"id":"Stu29","type":"Student"}}},"parents":[],"uid":{"__entity":{"id":"GT0C0A1SStu29","type":"Grade"}}},{"attrs":{"assignment":{"__entity":{"id":"T0C1A0","type":"Assignment"}},"student":{"__entity":{"id":"Stu29","type":"Student"}}},"parents":[],"uid":{"__entity":{"id":"GT0C1A0SStu29","type":"Grade"}}},{"attrs":{"assignment":{"__entity":{"id":"T0C1A1","type":"Assignment"}},"student":{"__entity":{"id":"Stu29","type":"Student"}}},"parents":[],"uid":{"__entity":{"id":"GT0C1A1SStu29","type":"Grade"}}},{"attrs":{"assignment":{"__entity":{"id":"T0C1A2","type":"Assignment"}},"student":{"__entity":{"id":"Stu29","type":"Student"}}},"parents":[],"uid":{"__entity":{"id":"GT0C1A2SStu29","type":"Grade"}}},{"attrs":{"assignment":{"__entity":{"id":"T2C0A0","type":"Assignment"}},"student":{"__entity":{"id":"Stu29","type":"Student"}}},"parents":[],"uid":{"__entity":{"id":"GT2C0A0SStu29","type":"Grade"}}},{"attrs":{"assignment":{"__entity":{"id":"T0C0A0","type":"Assignment"}},"student":{"__entity":{"id":"Stu30","type":"Student"}}},"parents":[],"uid":{"__entity":{"id":"GT0C0A0SStu30","type":"Grade"}}},{"attrs":{"assignment":{"__entity":{"id":"T0C0A1","type":"Assignment"}},"student":{"__entity":{"id":"Stu30","type":"Student"}}},"parents":[],"uid":{"__entity":{"id":"GT0C0A1SStu30","type":"Grade"}}},{"attrs":{"assignment":{"__entity":{"id":"T0C1A0","type":"Assignment"}},"student":{"__entity":{"id":"Stu30","type":"Student"}}},"parents":[],"uid":{"__entity":{"id":"GT0C1A0SStu30","type":"Grade"}}},{"attrs":{"assignment":{"__entity":{"id":"T0C1A1","type":"Assignment"}},"student":{"__entity":{"id":"Stu30","type":"Student"}}},"parents":[],"uid":{"__entity":{"id":"GT0C1A1SStu30","type":"Grade"}}},{"attrs":{"assignment":{"__entity":{"id":"T0C1A2","type":"Assignment"}},"student":{"__entity":{"id":"Stu30","type":"Student"}}},"parents":[],"uid":{"__entity":{"id":"GT0C1A2SStu30","type":"Grade"}}},{"attrs":{"assignment":{"__entity":{"id":"T1C0A0","type":"Assignment"}},"student":{"__entity":{"id":"Stu30","type":"Student"}}},"parents":[],"uid":{"__entity":{"id":"GT1C0A0SStu30","type":"Grade"}}},{"attrs":{"assignment":{"__entity":{"id":"T2C0A0","type":"Assignment"}},"student":{"__entity":{"id":"Stu30","type":"Student"}}},"parents":[],"uid":{"__entity":{"id":"GT2C0A0SStu30","type":"Grade"}}},{"attrs":{"assignment":{"__entity":{"id":"T3C0A0","type":"Assignment"}},"student":{"__entity":{"id":"Stu30","type":"Student"}}},"parents":[],"uid":{"__entity":{"id":"GT3C0A0SStu30","type":"Grade"}}},{"attrs":{"assignment":{"__entity":{"id":"T3C0A1","type":"Assignment"}},"student":{"__entity":{"id":"Stu30","type":"Student"}}},"parents":[],"uid":{"__entity":{"id":"GT3C0A1SStu30","type":"Grade"}}},{"attrs":{"assignment":{"__entity":{"id":"T0C0A0","type":"Assignment"}},"student":{"__entity":{"id":"Stu31","type":"Student"}}},"parents":[],"uid":{"__entity":{"id":"GT0C0A0SStu31","type":"Grade"}}},{"attrs":{"assignment":{"__entity":{"id":"T0C0A1","type":"Assignment"}},"student":{"__entity":{"id":"Stu31","type":"Student"}}},"parents":[],"uid":{"__entity":{"id":"GT0C0A1SStu31","type":"Grade"}}},{"attrs":{"assignment":{"__entity":{"id":"T0C1A0","type":"Assignment"}},"student":{"__entity":{"id":"Stu31","type":"Student"}}},"parents":[],"uid":{"__entity":{"id":"GT0C1A0SStu31","type":"Grade"}}},{"attrs":{"assignment":{"__entity":{"id":"T0C1A1","type":"Assignment"}},"student":{"__entity":{"id":"Stu31","type":"Student"}}},"parents":[],"uid":{"__entity":{"id":"GT0C1A1SStu31","type":"Grade"}}},{"attrs":{"assignment":{"__entity":{"id":"T0C1A2","type":"Assignment"}},"student":{"__entity":{"id":"Stu31","type":"Student"}}},"parents":[],"uid":{"__entity":{"id":"GT0C1A2SStu31","type":"Grade"}}},{"attrs":{"assignment":{"__entity":{"id":"T1C0A0","type":"Assignment"}},"student":{"__entity":{"id":"Stu31","type":"Student"}}},"parents":[],"uid":{"__entity":{"id":"GT1C0A0SStu31","type":"Grade"}}},{"attrs":{"assignment":{"__entity":{"id":"T2C0A0","type":"Assignment"}},"student":{"__entity":{"id":"Stu31","type":"Student"}}},"parents":[],"uid":{"__entity":{"id":"GT2C0A0SStu31","type":"Grade"}}},{"attrs":{"assignment":{"__entity":{"id":"T2C0A0","type":"Assignment"}},"student":{"__entity":{"id":"Stu32","type":"Student"}}},"parents":[],"uid":{"__entity":{"id":"GT2C0A0SStu32","type":"Grade"}}},{"attrs":{"assignment":{"__entity":{"id":"T3C0A0","type":"Assignment"}},"student":{"__entity":{"id":"Stu32","type":"Student"}}},"parents":[],"uid":{"__entity":{"id":"GT3C0A0SStu32","type":"Grade"}}},{"attrs":{"assignment":{"__entity":{"id":"T3C0A1","type":"Assignment"}},"student":{"__entity":{"id":"Stu32","type":"Student"}}},"parents":[],"uid":{"__entity":{"id":"GT3C0A1SStu32","type":"Grade"}}},{"attrs":{"assignment":{"__entity":{"id":"T0C0A0","type":"Assignment"}},"student":{"__entity":{"id":"Stu33","type":"Student"}}},"parents":[],"uid":{"__entity":{"id":"GT0C0A0SStu33","type":"Grade"}}},{"attrs":{"assignment":{"__entity":{"id":"T0C0A1","type":"Assignment"}},"student":{"__entity":{"id":"Stu33","type":"Student"}}},"parents":[],"uid":{"__entity":{"id":"GT0C0A1SStu33","type":"Grade"}}},{"attrs":{"assignment":{"__entity":{"id":"T0C1A0","type":"Assignment"}},"student":{"__entity":{"id":"Stu33","type":"Student"}}},"parents":[],"uid":{"__entity":{"id":"GT0C1A0SStu33","type":"Grade"}}},{"attrs":{"assignment":{"__entity":{"id":"T0C1A1","type":"Assignment"}},"student":{"__entity":{"id":"Stu33","type":"Student"}}},"parents":[],"uid":{"__entity":{"id":"GT0C1A1SStu33","type":"Grade"}}},{"attrs":{"assignment":{"__entity":{"id":"T0C1A2","type":"Assignment"}},"student":{"__entity":{"id":"Stu33","type":"Student"}}},"parents":[],"uid":{"__entity":{"id":"GT0C1A2SStu33","type":"Grade"}}},{"attrs":{"assignment":{"__entity":{"id":"T1C0A0","type":"Assignment"}},"student":{"__entity":{"id":"Stu33","type":"Student"}}},"parents":[],"uid":{"__entity":{"id":"GT1C0A0SStu33","type":"Grade"}}},{"attrs":{"assignment":{"__entity":{"id":"T2C0A0","type":"Assignment"}},"student":{"__entity":{"id":"Stu33","type":"Student"}}},"parents":[],"uid":{"__entity":{"id":"GT2C0A0SStu33","type":"Grade"}}},{"attrs":{"assignment":{"__entity":{"id":"T3C0A0","type":"Assignment"}},"student":{"__entity":{"id":"Stu33","type":"Student"}}},"parents":[],"uid":{"__entity":{"id":"GT3C0A0SStu33","type":"Grade"}}},{"attrs":{"assignment":{"__entity":{"id":"T3C0A1","type":"Assignment"}},"student":{"__entity":{"id":"Stu33","type":"Student"}}},"parents":[],"uid":{"__entity":{"id":"GT3C0A1SStu33","type":"Grade"}}},{"attrs":{"assignment":{"__entity":{"id":"T0C0A0","type":"Assignment"}},"student":{"__entity":{"id":"Stu34","type":"Student"}}},"parents":[],"uid":{"__entity":{"id":"GT0C0A0SStu34","type":"Grade"}}},{"attrs":{"assignment":{"__entity":{"id":"T0C0A1","type":"Assignment"}},"student":{"__entity":{"id":"Stu34","type":"Student"}}},"parents":[],"uid":{"__entity":{"id":"GT0C0A1SStu34","type":"Grade"}}},{"attrs":{"assignment":{"__entity":{"id":"T1C0A0","type":"Assignment"}},"student":{"__entity":{"id":"Stu34","type":"Student"}}},"parents":[],"uid":{"__entity":{"id":"GT1C0A0SStu34","type":"Grade"}}},{"attrs":{"assignment":{"__entity":{"id":"T1C0A0","type":"Assignment"}},"student":{"__entity":{"id":"Stu35","type":"Student"}}},"parents":[],"uid":{"__entity":{"id":"GT1C0A0SStu35","type":"Grade"}}},{"attrs":{"assignment":{"__entity":{"id":"T2C0A0","type":"Assignment"}},"student":{"__entity":{"id":"Stu35","type":"Student"}}},"parents":[],"uid":{"__entity":{"id":"GT2C0A0SStu35","type":"Grade"}}},{"attrs":{"assignment":{"__entity":{"id":"T3C0A0","type":"Assignment"}},"student":{"__entity":{"id":"Stu35","type":"Student"}}},"parents":[],"uid":{"__entity":{"id":"GT3C0A0SStu35","type":"Grade"}}},{"attrs":{"assignment":{"__entity":{"id":"T3C0A1","type":"Assignment"}},"student":{"__entity":{"id":"Stu35","type":"Student"}}},"parents":[],"uid":{"__entity":{"id":"GT3C0A1SStu35","type":"Grade"}}},{"attrs":{"assignment":{"__entity":{"id":"T0C0A0","type":"Assignment"}},"student":{"__entity":{"id":"Stu36","type":"Student"}}},"parents":[],"uid":{"__entity":{"id":"GT0C0A0SStu36","type":"Grade"}}},{"attrs":{"assignment":{"__entity":{"id":"T0C0A1","type":"Assignment"}},"student":{"__entity":{"id":"Stu36","type":"Student"}}},"parents":[],"uid":{"__entity":{"id":"GT0C0A1SStu36","type":"Grade"}}},{"attrs":{"assignment":{"__entity":{"id":"T0C1A0","type":"Assignment"}},"student":{"__entity":{"id":"Stu36","type":"Student"}}},"parents":[],"uid":{"__entity":{"id":"GT0C1A0SStu36","type":"Grade"}}},{"attrs":{"assignment":{"__entity":{"id":"T0C1A1","type":"Assignment"}},"student":{"__entity":{"id":"Stu36","type":"Student"}}},"parents":[],"uid":{"__entity":{"id":"GT0C1A1SStu36","type":"Grade"}}},{"attrs":{"assignment":{"__entity":{"id":"T0C1A2","type":"Assignment"}},"student":{"__entity":{"id":"Stu36","type":"Student"}}},"parents":[],"uid":{"__entity":{"id":"GT0C1A2SStu36","type":"Grade"}}},{"attrs":{"assignment":{"__entity":{"id":"T1C0A0","type":"Assignment"}},"student":{"__entity":{"id":"Stu36","type":"Student"}}},"parents":[],"uid":{"__entity":{"id":"GT1C0A0SStu36","type":"Grade"}}},{"attrs":{"assignment":{"__entity":{"id":"T2C0A0","type":"Assignment"}},"student":{"__entity":{"id":"Stu36","type":"Student"}}},"parents":[],"uid":{"__entity":{"id":"GT2C0A0SStu36","type":"Grade"}}},{"attrs":{"assignment":{"__entity":{"id":"T3C0A0","type":"Assignment"}},"student":{"__entity":{"id":"Stu36","type":"Student"}}},"parents":[],"uid":{"__entity":{"id":"GT3C0A0SStu36","type":"Grade"}}},{"attrs":{"assignment":{"__entity":{"id":"T3C0A1","type":"Assignment"}},"student":{"__entity":{"id":"Stu36","type":"Student"}}},"parents":[],"uid":{"__entity":{"id":"GT3C0A1SStu36","type":"Grade"}}},{"attrs":{"assignment":{"__entity":{"id":"T0C0A0","type":"Assignment"}},"student":{"__entity":{"id":"Stu37","type":"Student"}}},"parents":[],"uid":{"__entity":{"id":"GT0C0A0SStu37","type":"Grade"}}},{"attrs":{"assignment":{"__entity":{"id":"T0C0A1","type":"Assignment"}},"student":{"__entity":{"id":"Stu37","type":"Student"}}},"parents":[],"uid":{"__entity":{"id":"GT0C0A1SStu37","type":"Grade"}}},{"attrs":{"assignment":{"__entity":{"id":"T0C1A0","type":"Assignment"}},"student":{"__entity":{"id":"Stu37","type":"Student"}}},"parents":[],"uid":{"__entity":{"id":"GT0C1A0SStu37","type":"Grade"}}},{"attrs":{"assignment":{"__entity":{"id":"T0C1A1","type":"Assignment"}},"student":{"__entity":{"id":"Stu37","type":"Student"}}},"parents":[],"uid":{"__entity":{"id":"GT0C1A1SStu37","type":"Grade"}}},{"attrs":{"assignment":{"__entity":{"id":"T0C1A2","type":"Assignment"}},"student":{"__entity":{"id":"Stu37","type":"Student"}}},"parents":[],"uid":{"__entity":{"id":"GT0C1A2SStu37","type":"Grade"}}},{"attrs":{"assignment":{"__entity":{"id":"T1C0A0","type":"Assignment"}},"student":{"__entity":{"id":"Stu37","type":"Student"}}},"parents":[],"uid":{"__entity":{"id":"GT1C0A0SStu37","type":"Grade"}}},{"attrs":{"assignment":{"__entity":{"id":"T2C0A0","type":"Assignment"}},"student":{"__entity":{"id":"Stu37","type":"Student"}}},"parents":[],"uid":{"__entity":{"id":"GT2C0A0SStu37","type":"Grade"}}},{"attrs":{"assignment":{"__entity":{"id":"T3C0A0","type":"Assignment"}},"student":{"__entity":{"id":"Stu37","type":"Student"}}},"parents":[],"uid":{"__entity":{"id":"GT3C0A0SStu37","type":"Grade"}}},{"attrs":{"assignment":{"__entity":{"id":"T3C0A1","type":"Assignment"}},"student":{"__entity":{"id":"Stu37","type":"Student"}}},"parents":[],"uid":{"__entity":{"id":"GT3C0A1SStu37","type":"Grade"}}},{"attrs":{"assignment":{"__entity":{"id":"T0C0A0","type":"Assignment"}},"student":{"__entity":{"id":"Stu38","type":"Student"}}},"parents":[],"uid":{"__entity":{"id":"GT0C0A0SStu38","type":"Grade"}}},{"attrs":{"assignment":{"__entity":{"id":"T0C0A1","type":"Assignment"}},"student":{"__entity":{"id":"Stu38","type":"Student"}}},"parents":[],"uid":{"__entity":{"id":"GT0C0A1SStu38","type":"Grade"}}},{"attrs":{"assignment":{"__entity":{"id":"T0C1A0","type":"Assignment"}},"student":{"__entity":{"id":"Stu38","type":"Student"}}},"parents":[],"uid":{"__entity":{"id":"GT0C1A0SStu38","type":"Grade"}}},{"attrs":{"assignment":{"__entity":{"id":"T0C1A1","type":"Assignment"}},"student":{"__entity":{"id":"Stu38","type":"Student"}}},"parents":[],"uid":{"__entity":{"id":"GT0C1A1SStu38","type":"Grade"}}},{"attrs":{"assignment":{"__entity":{"id":"T0C1A2","type":"Assignment"}},"student":{"__entity":{"id":"Stu38","type":"Student"}}},"parents":[],"uid":{"__entity":{"id":"GT0C1A2SStu38","type":"Grade"}}},{"attrs":{"assignment":{"__entity":{"id":"T1C0A0","type":"Assignment"}},"student":{"__entity":{"id":"Stu38","type":"Student"}}},"parents":[],"uid":{"__entity":{"id":"GT1C0A0SStu38","type":"Grade"}}},{"attrs":{"assignment":{"__entity":{"id":"T2C0A0","type":"Assignment"}},"student":{"__entity":{"id":"Stu38","type":"Student"}}},"parents":[],"uid":{"__entity":{"id":"GT2C0A0SStu38","type":"Grade"}}},{"attrs":{"assignment":{"__entity":{"id":"T3C0A0","type":"Assignment"}},"student":{"__entity":{"id":"Stu38","type":"Student"}}},"parents":[],"uid":{"__entity":{"id":"GT3C0A0SStu38","type":"Grade"}}},{"attrs":{"assignment":{"__entity":{"id":"T3C0A1","type":"Assignment"}},"student":{"__entity":{"id":"Stu38","type":"Student"}}},"parents":[],"uid":{"__entity":{"id":"GT3C0A1SStu38","type":"Grade"}}},{"attrs":{"assignment":{"__entity":{"id":"T3C0A0","type":"Assignment"}},"student":{"__entity":{"id":"Stu39","type":"Student"}}},"parents":[],"uid":{"__entity":{"id":"GT3C0A0SStu39","type":"Grade"}}},{"attrs":{"assignment":{"__entity":{"id":"T3C0A1","type":"Assignment"}},"student":{"__entity":{"id":"Stu39","type":"Student"}}},"parents":[],"uid":{"__entity":{"id":"GT3C0A1SStu39","type":"Grade"}}},{"attrs":{"assignment":{"__entity":{"id":"T0C0A0","type":"Assignment"}},"student":{"__entity":{"id":"Stu40","type":"Student"}}},"parents":[],"uid":{"__entity":{"id":"GT0C0A0SStu40","type":"Grade"}}},{"attrs":{"assignment":{"__entity":{"id":"T0C0A1","type":"Assignment"}},"student":{"__entity":{"id":"Stu40","type":"Student"}}},"parents":[],"uid":{"__entity":{"id":"GT0C0A1SStu40","type":"Grade"}}},{"attrs":{"assignment":{"__entity":{"id":"T0C1A0","type":"Assignment"}},"student":{"__entity":{"id":"Stu40","type":"Student"}}},"parents":[],"uid":{"__entity":{"id":"GT0C1A0SStu40","type":"Grade"}}},{"attrs":{"assignment":{"__entity":{"id":"T0C1A1","type":"Assignment"}},"student":{"__entity":{"id":"Stu40","type":"Student"}}},"parents":[],"uid":{"__entity":{"id":"GT0C1A1SStu40","type":"Grade"}}},{"attrs":{"assignment":{"__entity":{"id":"T0C1A2","type":"Assignment"}},"student":{"__entity":{"id":"Stu40","type":"Student"}}},"parents":[],"uid":{"__entity":{"id":"GT0C1A2SStu40","type":"Grade"}}},{"attrs":{"assignment":{"__entity":{"id":"T1C0A0","type":"Assignment"}},"student":{"__entity":{"id":"Stu40","type":"Student"}}},"parents":[],"uid":{"__entity":{"id":"GT1C0A0SStu40","type":"Grade"}}},{"attrs":{"assignment":{"__entity":{"id":"T0C1A0","type":"Assignment"}},"student":{"__entity":{"id":"Stu41","type":"Student"}}},"parents":[],"uid":{"__entity":{"id":"GT0C1A0SStu41","type":"Grade"}}},{"attrs":{"assignment":{"__entity":{"id":"T0C1A1","type":"Assignment"}},"student":{"__entity":{"id":"Stu41","type":"Student"}}},"parents":[],"uid":{"__entity":{"id":"GT0C1A1SStu41","type":"Grade"}}},{"attrs":{"assignment":{"__entity":{"id":"T0C1A2","type":"Assignment"}},"student":{"__entity":{"id":"Stu41","type":"Student"}}},"parents":[],"uid":{"__entity":{"id":"GT0C1A2SStu41","type":"Grade"}}},{"attrs":{"assignment":{"__entity":{"id":"T1C0A0","type":"Assignment"}},"student":{"__entity":{"id":"Stu41","type":"Student"}}},"parents":[],"uid":{"__entity":{"id":"GT1C0A0SStu41","type":"Grade"}}},{"attrs":{"assignment":{"__entity":{"id":"T2C0A0","type":"Assignment"}},"student":{"__entity":{"id":"Stu41","type":"Student"}}},"parents":[],"uid":{"__entity":{"id":"GT2C0A0SStu41","type":"Grade"}}},{"attrs":{"assignment":{"__entity":{"id":"T3C0A0","type":"Assignment"}},"student":{"__entity":{"id":"Stu41","type":"Student"}}},"parents":[],"uid":{"__entity":{"id":"GT3C0A0SStu41","type":"Grade"}}},{"attrs":{"assignment":{"__entity":{"id":"T3C0A1","type":"Assignment"}},"student":{"__entity":{"id":"Stu41","type":"Student"}}},"parents":[],"uid":{"__entity":{"id":"GT3C0A1SStu41","type":"Grade"}}},{"attrs":{"assignment":{"__entity":{"id":"T4C0A0","type":"Assignment"}},"student":{"__entity":{"id":"Stu41","type":"Student"}}},"parents":[],"uid":{"__entity":{"id":"GT4C0A0SStu41","type":"Grade"}}},{"attrs":{"assignment":{"__entity":{"id":"T0C0A0","type":"Assignment"}},"student":{"__entity":{"id":"Stu42","type":"Student"}}},"parents":[],"uid":{"__entity":{"id":"GT0C0A0SStu42","type":"Grade"}}},{"attrs":{"assignment":{"__entity":{"id":"T0C0A1","type":"Assignment"}},"student":{"__entity":{"id":"Stu42","type":"Student"}}},"parents":[],"uid":{"__entity":{"id":"GT0C0A1SStu42","type":"Grade"}}},{"attrs":{"assignment":{"__entity":{"id":"T0C1A0","type":"Assignment"}},"student":{"__entity":{"id":"Stu42","type":"Student"}}},"parents":[],"uid":{"__entity":{"id":"GT0C1A0SStu42","type":"Grade"}}},{"attrs":{"assignment":{"__entity":{"id":"T0C1A1","type":"Assignment"}},"student":{"__entity":{"id":"Stu42","type":"Student"}}},"parents":[],"uid":{"__entity":{"id":"GT0C1A1SStu42","type":"Grade"}}},{"attrs":{"assignment":{"__entity":{"id":"T0C1A2","type":"Assignment"}},"student":{"__entity":{"id":"Stu42","type":"Student"}}},"parents":[],"uid":{"__entity":{"id":"GT0C1A2SStu42","type":"Grade"}}},{"attrs":{"assignment":{"__entity":{"id":"T2C0A0","type":"Assignment"}},"student":{"__entity":{"id":"Stu42","type":"Student"}}},"parents":[],"uid":{"__entity":{"id":"GT2C0A0SStu42","type":"Grade"}}},{"attrs":{"assignment":{"__entity":{"id":"T4C0A0","type":"Assignment"}},"student":{"__entity":{"id":"Stu42","type":"Student"}}},"parents":[],"uid":{"__entity":{"id":"GT4C0A0SStu42","type":"Grade"}}},{"attrs":{"assignment":{"__entity":{"id":"T0C1A0","type":"Assignment"}},"student":{"__entity":{"id":"Stu43","type":"Student"}}},"parents":[],"uid":{"__entity":{"id":"GT0C1A0SStu43","type":"Grade"}}},{"attrs":{"assignment":{"__entity":{"id":"T0C1A1","type":"Assignment"}},"student":{"__entity":{"id":"Stu43","type":"Student"}}},"parents":[],"uid":{"__entity":{"id":"GT0C1A1SStu43","type":"Grade"}}},{"attrs":{"assignment":{"__entity":{"id":"T0C1A2","type":"Assignment"}},"student":{"__entity":{"id":"Stu43","type":"Student"}}},"parents":[],"uid":{"__entity":{"id":"GT0C1A2SStu43","type":"Grade"}}},{"attrs":{"assignment":{"__entity":{"id":"T0C0A0","type":"Assignment"}},"student":{"__entity":{"id":"Stu44","type":"Student"}}},"parents":[],"uid":{"__entity":{"id":"GT0C0A0SStu44","type":"Grade"}}},{"attrs":{"assignment":{"__entity":{"id":"T0C0A1","type":"Assignment"}},"student":{"__entity":{"id":"Stu44","type":"Student"}}},"parents":[],"uid":{"__entity":{"id":"GT0C0A1SStu44","type":"Grade"}}},{"attrs":{"assignment":{"__entity":{"id":"T2C0A0","type":"Assignment"}},"student":{"__entity":{"id":"Stu44","type":"Student"}}},"parents":[],"uid":{"__entity":{"id":"GT2C0A0SStu44","type":"Grade"}}},{"attrs":{"assignment":{"__entity":{"id":"T3C0A0","type":"Assignment"}},"student":{"__entity":{"id":"Stu44","type":"Student"}}},"parents":[],"uid":{"__entity":{"id":"GT3C0A0SStu44","type":"Grade"}}},{"attrs":{"assignment":{"__entity":{"id":"T3C0A1","type":"Assignment"}},"student":{"__entity":{"id":"Stu44","type":"Student"}}},"parents":[],"uid":{"__entity":{"id":"GT3C0A1SStu44","type":"Grade"}}},{"attrs":{"assignment":{"__entity":{"id":"T0C1A0","type":"Assignment"}},"student":{"__entity":{"id":"Stu45","type":"Student"}}},"parents":[],"uid":{"__entity":{"id":"GT0C1A0SStu45","type":"Grade"}}},{"attrs":{"assignment":{"__entity":{"id":"T0C1A1","type":"Assignment"}},"student":{"__entity":{"id":"Stu45","type":"Student"}}},"parents":[],"uid":{"__entity":{"id":"GT0C1A1SStu45","type":"Grade"}}},{"attrs":{"assignment":{"__entity":{"id":"T0C1A2","type":"Assignment"}},"student":{"__entity":{"id":"Stu45","type":"Student"}}},"parents":[],"uid":{"__entity":{"id":"GT0C1A2SStu45","type":"Grade"}}},{"attrs":{"assignment":{"__entity":{"id":"T4C0A0","type":"Assignment"}},"student":{"__entity":{"id":"Stu45","type":"Student"}}},"parents":[],"uid":{"__entity":{"id":"GT4C0A0SStu45","type":"Grade"}}},{"attrs":{"assignment":{"__entity":{"id":"T0C0A0","type":"Assignment"}},"student":{"__entity":{"id":"Stu46","type":"Student"}}},"parents":[],"uid":{"__entity":{"id":"GT0C0A0SStu46","type":"Grade"}}},{"attrs":{"assignment":{"__entity":{"id":"T0C0A1","type":"Assignment"}},"student":{"__entity":{"id":"Stu46","type":"Student"}}},"parents":[],"uid":{"__entity":{"id":"GT0C0A1SStu46","type":"Grade"}}},{"attrs":{"assignment":{"__entity":{"id":"T0C1A0","type":"Assignment"}},"student":{"__entity":{"id":"Stu46","type":"Student"}}},"parents":[],"uid":{"__entity":{"id":"GT0C1A0SStu46","type":"Grade"}}},{"attrs":{"assignment":{"__entity":{"id":"T0C1A1","type":"Assignment"}},"student":{"__entity":{"id":"Stu46","type":"Student"}}},"parents":[],"uid":{"__entity":{"id":"GT0C1A1SStu46","type":"Grade"}}},{"attrs":{"assignment":{"__entity":{"id":"T0C1A2","type":"Assignment"}},"student":{"__entity":{"id":"Stu46","type":"Student"}}},"parents":[],"uid":{"__entity":{"id":"GT0C1A2SStu46","type":"Grade"}}},{"attrs":{"assignment":{"__entity":{"id":"T3C0A0","type":"Assignment"}},"student":{"__entity":{"id":"Stu46","type":"Student"}}},"parents":[],"uid":{"__entity":{"id":"GT3C0A0SStu46","type":"Grade"}}},{"attrs":{"assignment":{"__entity":{"id":"T3C0A1","type":"Assignment"}},"student":{"__entity":{"id":"Stu46","type":"Student"}}},"parents":[],"uid":{"__entity":{"id":"GT3C0A1SStu46","type":"Grade"}}},{"attrs":{"assignment":{"__entity":{"id":"T4C0A0","type":"Assignment"}},"student":{"__entity":{"id":"Stu47","type":"Student"}}},"parents":[],"uid":{"__entity":{"id":"GT4C0A0SStu47","type":"Grade"}}},{"attrs":{"assignment":{"__entity":{"id":"T0C0A0","type":"Assignment"}},"student":{"__entity":{"id":"Stu48","type":"Student"}}},"parents":[],"uid":{"__entity":{"id":"GT0C0A0SStu48","type":"Grade"}}},{"attrs":{"assignment":{"__entity":{"id":"T0C0A1","type":"Assignment"}},"student":{"__entity":{"id":"Stu48","type":"Student"}}},"parents":[],"uid":{"__entity":{"id":"GT0C0A1SStu48","type":"Grade"}}},{"attrs":{"assignment":{"__entity":{"id":"T0C1A0","type":"Assignment"}},"student":{"__entity":{"id":"Stu49","type":"Student"}}},"parents":[],"uid":{"__entity":{"id":"GT0C1A0SStu49","type":"Grade"}}},{"attrs":{"assignment":{"__entity":{"id":"T0C1A1","type":"Assignment"}},"student":{"__entity":{"id":"Stu49","type":"Student"}}},"parents":[],"uid":{"__entity":{"id":"GT0C1A1SStu49","type":"Grade"}}},{"attrs":{"assignment":{"__entity":{"id":"T0C1A2","type":"Assignment"}},"student":{"__entity":{"id":"Stu49","type":"Student"}}},"parents":[],"uid":{"__entity":{"id":"GT0C1A2SStu49","type":"Grade"}}},{"attrs":{"assignment":{"__entity":{"id":"T1C0A0","type":"Assignment"}},"student":{"__entity":{"id":"Stu49","type":"Student"}}},"parents":[],"uid":{"__entity":{"id":"GT1C0A0SStu49","type":"Grade"}}},{"attrs":{"assignment":{"__entity":{"id":"T2C0A0","type":"Assignment"}},"student":{"__entity":{"id":"Stu49","type":"Student"}}},"parents":[],"uid":{"__entity":{"id":"GT2C0A0SStu49","type":"Grade"}}},{"attrs":{"assignment":{"__entity":{"id":"T3C0A0","type":"Assignment"}},"student":{"__entity":{"id":"Stu49","type":"Student"}}},"parents":[],"uid":{"__entity":{"id":"GT3C0A0SStu49","type":"Grade"}}},{"attrs":{"assignment":{"__entity":{"id":"T3C0A1","type":"Assignment"}},"student":{"__entity":{"id":"Stu49","type":"Student"}}},"parents":[],"uid":{"__entity":{"id":"GT3C0A1SStu49","type":"Grade"}}},{"attrs":{"assignment":{"__entity":{"id":"T4C0A0","type":"Assignment"}},"student":{"__entity":{"id":"Stu49","type":"Student"}}},"parents":[],"uid":{"__entity":{"id":"GT4C0A0SStu49","type":"Grade"}}}]